bdnb_client/__init__.py
bdnb_client/_base_client.py
bdnb_client/_client.py
bdnb_client/_compat.py
bdnb_client/_constants.py
bdnb_client/_exceptions.py
bdnb_client/_files.py
bdnb_client/_models.py
bdnb_client/_qs.py
bdnb_client/_resource.py
bdnb_client/_response.py
bdnb_client/_streaming.py
bdnb_client/_types.py
bdnb_client/_version.py
bdnb_client/pagination.py
bdnb_client/py.typed
bdnb_client/_utils/__init__.py
bdnb_client/_utils/_logs.py
bdnb_client/_utils/_proxy.py
bdnb_client/_utils/_reflection.py
bdnb_client/_utils/_streams.py
bdnb_client/_utils/_sync.py
bdnb_client/_utils/_transform.py
bdnb_client/_utils/_typing.py
bdnb_client/_utils/_utils.py
bdnb_client/lib/.keep
bdnb_client/resources/__init__.py
bdnb_client/resources/autocompletion.py
bdnb_client/resources/donnees/__init__.py
bdnb_client/resources/donnees/adresse.py
bdnb_client/resources/donnees/ancqpv.py
bdnb_client/resources/donnees/batiment_construction.py
bdnb_client/resources/donnees/donnees.py
bdnb_client/resources/donnees/proprietaire.py
bdnb_client/resources/donnees/batiment_groupe/__init__.py
bdnb_client/resources/donnees/batiment_groupe/adresse.py
bdnb_client/resources/donnees/batiment_groupe/argiles.py
bdnb_client/resources/donnees/batiment_groupe/batiment_groupe.py
bdnb_client/resources/donnees/batiment_groupe/bdtopo_bat.py
bdnb_client/resources/donnees/batiment_groupe/bdtopo_equ.py
bdnb_client/resources/donnees/batiment_groupe/bdtopo_zoac.py
bdnb_client/resources/donnees/batiment_groupe/bpe.py
bdnb_client/resources/donnees/batiment_groupe/delimitation_enveloppe.py
bdnb_client/resources/donnees/batiment_groupe/dle_elec_2020.py
bdnb_client/resources/donnees/batiment_groupe/dle_elec_multimillesime.py
bdnb_client/resources/donnees/batiment_groupe/dle_gaz_2020.py
bdnb_client/resources/donnees/batiment_groupe/dle_gaz_multimillesime.py
bdnb_client/resources/donnees/batiment_groupe/dle_reseaux_2020.py
bdnb_client/resources/donnees/batiment_groupe/dle_reseaux_multimillesime.py
bdnb_client-0.0.9.dist-info/METADATA
bdnb_client-0.0.9.dist-info/WHEEL
bdnb_client-0.0.9.dist-info/licenses/LICENSE
bdnb_client-0.0.9.dist-info/RECORD
